MufSim-1.2.2.dist-info/DESCRIPTION.rst
MufSim-1.2.2.dist-info/METADATA
MufSim-1.2.2.dist-info/RECORD
MufSim-1.2.2.dist-info/WHEEL
MufSim-1.2.2.dist-info/entry_points.txt
MufSim-1.2.2.dist-info/metadata.json
MufSim-1.2.2.dist-info/top_level.txt
mufsim/__init__.py
mufsim/callframe.py
mufsim/commands.py
mufsim/compiled.py
mufsim/compiler.py
mufsim/configs.py
mufsim/errors.py
mufsim/events.py
mufsim/gamedb.py
mufsim/interface.py
mufsim/locks.py
mufsim/logger.py
mufsim/process.py
mufsim/processlist.py
mufsim/stackitems.py
mufsim/sysparms.py
mufsim/utils.py
mufsim/console/__init__.py
mufsim/gui/__init__.py
mufsim/gui/listdisplay.py
mufsim/gui/menudecorators.py
mufsim/gui/mufeditor.py
mufsim/gui/upload_wizard.py
mufsim/insts/__init__.py
mufsim/insts/arrays.py
mufsim/insts/base.py
mufsim/insts/comparators.py
mufsim/insts/connections.py
mufsim/insts/debug.py
mufsim/insts/descriptors.py
mufsim/insts/directives.py
mufsim/insts/events.py
mufsim/insts/flow.py
mufsim/insts/fpmath.py
mufsim/insts/intmath.py
mufsim/insts/io.py
mufsim/insts/locks.py
mufsim/insts/mcp.py
mufsim/insts/mcpgui.py
mufsim/insts/objectdb.py
mufsim/insts/predicates.py
mufsim/insts/process.py
mufsim/insts/properties.py
mufsim/insts/stack.py
mufsim/insts/strings.py
mufsim/insts/timedate.py
