Metadata-Version: 2.0
Name: MufSim
Version: 1.2.2
Summary: Muf language simulator and debugger.
Home-page: https://github.com/revarbat/mufsim
Author: Revar Desmera
Author-email: revarbat@gmail.com
License: MIT License
Download-URL: https://github.com/revarbat/mufsim/archive/master.zip
Keywords: muf muv debugger development
Platform: UNKNOWN
Classifier: Development Status :: 4 - Beta
Classifier: Environment :: Console
Classifier: Environment :: Web Environment
Classifier: Intended Audience :: End Users/Desktop
Classifier: Intended Audience :: Developers
Classifier: Intended Audience :: Other Audience
Classifier: License :: OSI Approved :: MIT License
Classifier: Operating System :: MacOS :: MacOS X
Classifier: Operating System :: Microsoft :: Windows
Classifier: Operating System :: POSIX
Classifier: Programming Language :: Python :: 2
Classifier: Programming Language :: Python :: 2.7
Classifier: Programming Language :: Python :: 3
Classifier: Programming Language :: Python :: 3.5
Classifier: Topic :: Software Development :: Compilers
Classifier: Topic :: Software Development :: Debuggers
Classifier: Topic :: Software Development :: Interpreters
Classifier: Topic :: Software Development :: Testing
Requires-Dist: appdirs (>=1.4.0)
Requires-Dist: belfrywidgets (>=1.0.3)
Requires-Dist: mudclientprotocol (>=0.1.0)
Requires-Dist: packaging
Requires-Dist: pymuv (>=0.9.8)
Requires-Dist: setuptools
Requires-Dist: six
Requires-Dist: ssltelnet (>=0.9.2)
